jupyter_leaflet_bis/__init__.py
jupyter_leaflet_bis-0.20.4.data/data/share/jupyter/labextensions/jupyter-leaflet/package.json
jupyter_leaflet_bis-0.20.4.data/data/share/jupyter/labextensions/jupyter-leaflet/static/00179c4c1ee830d3a108.png
jupyter_leaflet_bis-0.20.4.data/data/share/jupyter/labextensions/jupyter-leaflet/static/0194f340b27a4c5be35b.png
jupyter_leaflet_bis-0.20.4.data/data/share/jupyter/labextensions/jupyter-leaflet/static/066daca850d8ffbef007.png
jupyter_leaflet_bis-0.20.4.data/data/share/jupyter/labextensions/jupyter-leaflet/static/10.a870c234dbfb9d633196.js
jupyter_leaflet_bis-0.20.4.data/data/share/jupyter/labextensions/jupyter-leaflet/static/142.2229eb2b30be0164dcb8.js
jupyter_leaflet_bis-0.20.4.data/data/share/jupyter/labextensions/jupyter-leaflet/static/1755d22b1ffb0e8589b2.png
jupyter_leaflet_bis-0.20.4.data/data/share/jupyter/labextensions/jupyter-leaflet/static/176.e78fbd7758600d806691.js
jupyter_leaflet_bis-0.20.4.data/data/share/jupyter/labextensions/jupyter-leaflet/static/180.13bfbd8bd9eccd3798e1.js
jupyter_leaflet_bis-0.20.4.data/data/share/jupyter/labextensions/jupyter-leaflet/static/189.569def7b38a86f0bff16.js
jupyter_leaflet_bis-0.20.4.data/data/share/jupyter/labextensions/jupyter-leaflet/static/1d58b682e64eeac7a47f.png
jupyter_leaflet_bis-0.20.4.data/data/share/jupyter/labextensions/jupyter-leaflet/static/1dbbe9d028e292f36fcb.png
jupyter_leaflet_bis-0.20.4.data/data/share/jupyter/labextensions/jupyter-leaflet/static/256.1678b3c88ad1a83079b8.js
jupyter_leaflet_bis-0.20.4.data/data/share/jupyter/labextensions/jupyter-leaflet/static/264f5c640339f042dd72.png
jupyter_leaflet_bis-0.20.4.data/data/share/jupyter/labextensions/jupyter-leaflet/static/268.0235d96e5b8b7dcf571e.js
jupyter_leaflet_bis-0.20.4.data/data/share/jupyter/labextensions/jupyter-leaflet/static/269.8ccdd4f07c1457c468c0.js
jupyter_leaflet_bis-0.20.4.data/data/share/jupyter/labextensions/jupyter-leaflet/static/280.f12216d4249b12b745b5.js
jupyter_leaflet_bis-0.20.4.dist-info/METADATA
jupyter_leaflet_bis-0.20.4.dist-info/WHEEL
jupyter_leaflet_bis-0.20.4.dist-info/licenses/LICENSE
jupyter_leaflet_bis-0.20.4.dist-info/RECORD
