Metadata-Version: 2.4
Name: jupyter-leaflet-bis
Version: 0.20.4
Summary: ipyleaflet extensions for JupyterLab and Jupyter Notebook
Project-URL: Homepage, https://github.com/jupyter-widgets/ipyleaflet
Author-email: Project Jupyter <jupyter@googlegroups.com>
License: The MIT License (MIT)
License-File: LICENSE
Keywords: GIS,graphics,ipython,jupyter,widgets
Classifier: Intended Audience :: Developers
Classifier: Intended Audience :: Science/Research
Classifier: License :: OSI Approved :: MIT License
Classifier: Programming Language :: Python :: 3.10
Classifier: Programming Language :: Python :: 3.11
Classifier: Programming Language :: Python :: 3.12
Classifier: Topic :: Multimedia :: Graphics
Requires-Python: >=3.10
